{
  "minecraft:recipes/building_blocks/andesite_stairs_from_andesite_stonecutting": {
    "criteria": {
      "has_andesite": "2024-11-09 13:45:56 +0000"
    },
    "done": true
  },
  "minecraft:recipes/misc/copper_ingot_from_blasting_raw_copper": {
    "criteria": {
      "has_raw_copper": "2024-11-09 13:45:56 +0000"
    },
    "done": true
  },
  "minecraft:recipes/building_blocks/raw_copper_block": {
    "criteria": {
      "has_raw_copper": "2024-11-09 13:45:56 +0000"
    },
    "done": true
  },
  "minecraft:recipes/building_blocks/granite_stairs": {
    "criteria": {
      "has_granite": "2024-11-09 13:45:56 +0000"
    },
    "done": true
  },
  "minecraft:recipes/building_blocks/granite_stairs_from_granite_stonecutting": {
    "criteria": {
      "has_granite": "2024-11-09 13:45:56 +0000"
    },
    "done": true
  },
  "minecraft:recipes/decorations/granite_wall": {
    "criteria": {
      "has_granite": "2024-11-09 13:45:56 +0000"
    },
    "done": true
  },
  "minecraft:recipes/building_blocks/andesite_stairs": {
    "criteria": {
      "has_andesite": "2024-11-09 13:45:56 +0000"
    },
    "done": true
  },
  "minecraft:recipes/building_blocks/polished_granite_slab_from_granite_stonecutting": {
    "criteria": {
      "has_granite": "2024-11-09 13:45:56 +0000"
    },
    "done": true
  },
  "minecraft:recipes/building_blocks/polished_andesite_from_andesite_stonecutting": {
    "criteria": {
      "has_andesite": "2024-11-09 13:45:56 +0000"
    },
    "done": true
  },
  "minecraft:recipes/building_blocks/granite_slab_from_granite_stonecutting": {
    "criteria": {
      "has_granite": "2024-11-09 13:45:56 +0000"
    },
    "done": true
  },
  "minecraft:recipes/building_blocks/polished_andesite": {
    "criteria": {
      "has_andesite": "2024-11-09 13:45:56 +0000"
    },
    "done": true
  },
  "minecraft:recipes/decorations/andesite_wall_from_andesite_stonecutting": {
    "criteria": {
      "has_andesite": "2024-11-09 13:45:56 +0000"
    },
    "done": true
  },
  "minecraft:recipes/building_blocks/polished_granite": {
    "criteria": {
      "has_granite": "2024-11-09 13:45:56 +0000"
    },
    "done": true
  },
  "minecraft:recipes/decorations/crafting_table": {
    "criteria": {
      "unlock_right_away": "2024-11-09 13:45:23 +0000"
    },
    "done": true
  },
  "minecraft:recipes/building_blocks/polished_andesite_slab_from_andesite_stonecutting": {
    "criteria": {
      "has_andesite": "2024-11-09 13:45:56 +0000"
    },
    "done": true
  },
  "minecraft:adventure/root": {
    "criteria": {
      "killed_by_something": "2024-11-09 13:46:23 +0000"
    },
    "done": true
  },
  "minecraft:recipes/decorations/granite_wall_from_granite_stonecutting": {
    "criteria": {
      "has_granite": "2024-11-09 13:45:56 +0000"
    },
    "done": true
  },
  "minecraft:adventure/adventuring_time": {
    "criteria": {
      "minecraft:snowy_plains": "2024-11-09 13:45:24 +0000"
    },
    "done": false
  },
  "minecraft:recipes/decorations/andesite_wall": {
    "criteria": {
      "has_andesite": "2024-11-09 13:45:56 +0000"
    },
    "done": true
  },
  "minecraft:recipes/building_blocks/andesite_slab": {
    "criteria": {
      "has_andesite": "2024-11-09 13:45:56 +0000"
    },
    "done": true
  },
  "minecraft:recipes/building_blocks/polished_andesite_stairs_from_andesite_stonecutting": {
    "criteria": {
      "has_andesite": "2024-11-09 13:45:56 +0000"
    },
    "done": true
  },
  "minecraft:recipes/building_blocks/polished_granite_from_granite_stonecutting": {
    "criteria": {
      "has_granite": "2024-11-09 13:45:56 +0000"
    },
    "done": true
  },
  "minecraft:recipes/building_blocks/granite_slab": {
    "criteria": {
      "has_granite": "2024-11-09 13:45:56 +0000"
    },
    "done": true
  },
  "minecraft:recipes/building_blocks/polished_granite_stairs_from_granite_stonecutting": {
    "criteria": {
      "has_granite": "2024-11-09 13:45:56 +0000"
    },
    "done": true
  },
  "minecraft:recipes/building_blocks/andesite_slab_from_andesite_stonecutting": {
    "criteria": {
      "has_andesite": "2024-11-09 13:45:56 +0000"
    },
    "done": true
  },
  "minecraft:recipes/misc/copper_ingot_from_smelting_raw_copper": {
    "criteria": {
      "has_raw_copper": "2024-11-09 13:45:56 +0000"
    },
    "done": true
  },
  "DataVersion": 3465
}